ml_easy_setup/__init__.py
ml_easy_setup/cli.py
ml_easy_setup/webui.py
ml_easy_setup/core/__init__.py
ml_easy_setup/core/container.py
ml_easy_setup/core/detector.py
ml_easy_setup/core/distributed.py
ml_easy_setup/core/env_manager.py
ml_easy_setup/core/health.py
ml_easy_setup/core/resolver.py
ml_easy_setup/core/template.py
ml_easy_setup/sdk/__init__.py
ml_easy_setup/sdk/magic.py
ml_easy_setup/sdk/models/__init__.py
ml_easy_setup/sdk/models/simple.py
ml_easy_setup/sdk/trainers/__init__.py
ml_easy_setup/sdk/trainers/auto.py
ml_easy_setup/sdk/utils/__init__.py
ml_easy_setup/sdk/utils/device.py
ml_easy_setup/sdk/utils/types.py
ml_easy_setup/utils/__init__.py
ml_easy_setup/utils/system.py
ml_easy_setup-0.7.0.dist-info/METADATA
ml_easy_setup-0.7.0.dist-info/WHEEL
ml_easy_setup-0.7.0.dist-info/entry_points.txt
ml_easy_setup-0.7.0.dist-info/licenses/LICENSE
ml_easy_setup-0.7.0.dist-info/RECORD
