Metadata-Version: 2.4
Name: ml-easy-setup
Version: 0.7.0
Summary: 一键配置机器学习/深度学习环境，解决依赖冲突和配置难题
Project-URL: Homepage, https://github.com/YuanyuanMa03/ml-easy-setup
Project-URL: Documentation, https://github.com/YuanyuanMa03/ml-easy-setup#readme
Project-URL: Repository, https://github.com/YuanyuanMa03/ml-easy-setup
Project-URL: Bug Tracker, https://github.com/YuanyuanMa03/ml-easy-setup/issues
Author-email: YuanyuanMa <your.email@example.com>
License: MIT
License-File: LICENSE
Keywords: cuda,deep-learning,environment,machine-learning,pytorch,setup,training
Classifier: Development Status :: 3 - Alpha
Classifier: Intended Audience :: Developers
Classifier: Intended Audience :: Science/Research
Classifier: Programming Language :: Python :: 3
Classifier: Programming Language :: Python :: 3.10
Classifier: Programming Language :: Python :: 3.11
Classifier: Programming Language :: Python :: 3.12
Requires-Python: >=3.10
Requires-Dist: click>=8.1.0
Requires-Dist: packaging>=23.0
Requires-Dist: pyyaml>=6.0
Requires-Dist: rich>=13.0.0
Provides-Extra: dev
Requires-Dist: black>=23.0; extra == 'dev'
Requires-Dist: mypy>=1.0; extra == 'dev'
Requires-Dist: pytest-cov>=4.0; extra == 'dev'
Requires-Dist: pytest>=7.0; extra == 'dev'
Requires-Dist: ruff>=0.1.0; extra == 'dev'
Provides-Extra: sdk
Requires-Dist: torch>=2.0.0; extra == 'sdk'
Requires-Dist: tqdm>=4.65.0; extra == 'sdk'
Provides-Extra: webui
Requires-Dist: streamlit>=1.28.0; extra == 'webui'
